capitalist/__init__.py
capitalist/_compat.py
capitalist/core.py
py_capitalist-0.1.dist-info/DESCRIPTION.rst
py_capitalist-0.1.dist-info/METADATA
py_capitalist-0.1.dist-info/RECORD
py_capitalist-0.1.dist-info/WHEEL
py_capitalist-0.1.dist-info/metadata.json
py_capitalist-0.1.dist-info/top_level.txt
