Metadata-Version: 2.0
Name: py-capitalist
Version: 0.1
Summary: Python client library for Capitalist API
Home-page: https://github.com/Stranger6667/py-capitalist
Author: Dmitry Dygalo
Author-email: dadygalo@gmail.com
License: MIT
Keywords: capitalist,api,client,payments
Platform: UNKNOWN
Classifier: Development Status :: 4 - Beta
Classifier: Environment :: Console
Classifier: Intended Audience :: Developers
Classifier: Operating System :: OS Independent
Classifier: License :: OSI Approved :: MIT License
Classifier: Programming Language :: Python
Classifier: Programming Language :: Python :: 2
Classifier: Programming Language :: Python :: 2.7
Classifier: Programming Language :: Python :: 3
Classifier: Programming Language :: Python :: 3.3
Classifier: Programming Language :: Python :: 3.4
Classifier: Programming Language :: Python :: 3.5
Classifier: Programming Language :: Python :: 3.6
Classifier: Programming Language :: Python :: Implementation :: CPython
Requires-Dist: requests
Requires-Dist: pycrypto
